tcinvest_mcp_server/__init__.py
tcinvest_mcp_server/__main__.py
tcinvest_mcp_server/constant.py
tcinvest_mcp_server/server.py
tcinvest_mcp_server/api/__init__.py
tcinvest_mcp_server/api/client.py
tcinvest_mcp_server/services/__init__.py
tcinvest_mcp_server/services/athena.py
tcinvest_mcp_server/services/bond_trading.py
tcinvest_mcp_server/services/icalendar_service.py
tcinvest_mcp_server/services/stock_insight.py
tcinvest_mcp_server/services/ta.py
tcinvest_mcp_server/services/tcanalysis.py
tcinvest_mcp_server-0.1.3.dist-info/licenses/LICENSE
tcinvest_mcp_server-0.1.3.dist-info/METADATA
tcinvest_mcp_server-0.1.3.dist-info/WHEEL
tcinvest_mcp_server-0.1.3.dist-info/entry_points.txt
tcinvest_mcp_server-0.1.3.dist-info/top_level.txt
tcinvest_mcp_server-0.1.3.dist-info/RECORD
