Metadata-Version: 2.4
Name: tcinvest-mcp-server
Version: 0.1.3
Summary: A Model Context Protocol (MCP) server for TCInvest, enabling LLM-powered access to TCBS stock and bond data.
Author-email: hoangpd <phamdinhhoang.fetk54@gmail.com>
Requires-Python: >=3.8
License-File: LICENSE
Requires-Dist: requests
Requires-Dist: python-dotenv
Requires-Dist: matplotlib
Requires-Dist: pydantic
Dynamic: license-file
